jrm33/Globals.py
jrm33/Model.py
jrm33/ModelCart.py
jrm33/Test.py
jrm33/_CoeffGrids.py
jrm33/_Legendre.py
jrm33/_ReadCoeffs.py
jrm33/_ScaledCoeffs.py
jrm33/_Schmidt.py
jrm33/_SphHarm.py
jrm33/__init__.py
jrm33/__data/coeffs.dat
jrm33-1.0.3.dist-info/LICENSE
jrm33-1.0.3.dist-info/METADATA
jrm33-1.0.3.dist-info/WHEEL
jrm33-1.0.3.dist-info/top_level.txt
jrm33-1.0.3.dist-info/RECORD
