Metadata-Version: 2.1
Name: jrm33
Version: 1.0.3
Summary: Python implementation of the JRM33 model
Home-page: https://github.com/mattkjames7/jrm33
Author: Matthew Knight James
Author-email: mattkjames7@gmail.com
License: UNKNOWN
Platform: UNKNOWN
Classifier: Programming Language :: Python :: 3
Classifier: License :: OSI Approved :: MIT License
Classifier: Operating System :: POSIX
License-File: LICENSE
Requires-Dist: numpy
Requires-Dist: PyFileIO
